[[{"text":" ◼ ◼         ◼    ◼      ◼◼◼ ◼     ◼ ◼       ◼◼   ◼◼◼◼◼◼◼\n◼◼ ◼       ◼◼◼◼◼              ◼◼◼◼◼◼◼◼  ◼                \n◼◼ ◼◼◼   ◼◼                      ◼ ◼◼◼  ◼◼◼◼◼◼◼◼◼◼◼◼◼◼◼◼◼\n◼◼ ◼  ◼ ◼                          ◼◼◼ ◼◼◼◼◼◼◼◼◼◼◼◼      \n","color":"#ffffff","alpha":0.2,"rows_above":0},{"text":"◼◼ ◼             ◼◼         ◼ ◼    ◼ ◼ ◼◼◼◼◼◼◼◼◼◼◼◼◼◼    \n◼◼ ◼      ◼◼◼                  ◼   ◼◼◼                ◼◼◼\n◼◼ ◼ ◼◼  ◼                        ◼◼◼◼  ◼◼◼◼◼◼◼◼◼◼◼◼◼◼◼◼◼\n◼◼ ◼   ◼                           ◼◼◼ ◼◼               ◼\n","color":"#ffffff","alpha":0.2,"rows_above":0}],[{"text":"  ◼                ◼◼◼ ◼◼                                \n  ◼                          ◼                           \n  ◼        ◼                    ◼                        \n  ◼      ◼                        ◼                      \n","color":"#ffffff","alpha":0.4,"rows_above":0},{"text":"  ◼                       ◼◼ ◼                           \n  ◼                                                      \n  ◼       ◼                      ◼                       \n  ◼     ◼                                                \n","color":"#ffffff","alpha":0.4,"rows_above":0}],[{"text":"                      ◼                                  \n                ◼           ◼                            \n                                                         \n                                                         \n","color":"#ffffff","alpha":0.6,"rows_above":0},{"text":"                   ◼◼◼◼◼◼◼                               \n             ◼                ◼                          \n                                                         \n                                                         \n","color":"#ffffff","alpha":0.6,"rows_above":0}],[{"text":"                                                         \n                 ◼◼◼◼◼◼◼◼◼◼◼                             \n            ◼◼◼◼◼◼◼◼◼◼◼◼◼◼◼◼◼◼◼◼                         \n          ◼◼◼◼◼◼◼◼◼◼◼◼◼◼◼◼◼◼◼◼◼◼◼◼                       \n","color":"#ffffff","alpha":0.8,"rows_above":0},{"text":"                                                         \n              ◼◼◼◼◼◼◼◼◼◼◼◼◼◼◼◼                           \n           ◼◼◼◼◼◼◼◼◼◼◼◼◼◼◼◼◼◼◼◼◼◼                        \n         ◼◼◼◼◼◼◼◼◼◼◼◼◼◼◼◼◼◼◼◼◼◼◼◼◼◼                      \n","color":"#ffffff","alpha":0.8,"rows_above":0}],[{"text":"◼◼ ◼◼◼◼◼                            ◼◼ ◼◼◼◼◼◼◼◼◼◼◼◼◼     \n◼◼ ◼ ◼◼◼                                  ◼◼◼◼◼◼◼◼◼◼◼◼◼◼◼\n◼◼ ◼◼◼◼                                ◼◼◼◼◼◼◼◼◼◼◼◼◼◼◼◼◼◼\n◼◼ ◼ ◼◼◼                                 ◼◼◼◼◼◼◼◼◼◼◼◼◼◼◼◼\n","color":"#ffffff","alpha":0.2,"rows_above":8},{"text":"◼◼ ◼ ◼◼◼                             ◼◼◼◼ ◼◼◼◼◼◼◼◼       \n◼◼ ◼   ◼                              ◼◼◼                \n◼◼ ◼◼◼◼                               ◼◼ ◼◼◼◼◼◼◼◼◼◼◼◼◼◼◼◼\n◼◼◼◼◼◼◼◼                                ◼              ◼◼\n","color":"#ffffff","alpha":0.2,"rows_above":8}],[{"text":"  ◼     ◼                          ◼                ◼◼◼◼◼\n  ◼                                  ◼◼◼◼◼               \n  ◼    ◼                             ◼                   \n  ◼                  ◼                ◼◼◼                \n","color":"#ffffff","alpha":0.4,"rows_above":8},{"text":"  ◼                                 ◼    ◼        ◼◼◼◼◼◼◼\n  ◼                                  ◼                   \n  ◼    ◼                                ◼                \n                  ◼◼◼                  ◼                 \n","color":"#ffffff","alpha":0.4,"rows_above":8}],[{"text":"                                                         \n             ◼◼ ◼                   ◼                    \n           ◼◼◼◼◼◼◼◼                                      \n          ◼◼◼◼◼◼◼◼◼◼◼ ◼◼◼                                \n","color":"#ffffff","alpha":0.6,"rows_above":8},{"text":"        ◼                                                \n            ◼◼◼◼◼◼◼                                      \n          ◼◼◼◼◼◼◼◼                                       \n           ◼◼◼◼◼◼◼   ◼◼◼                                 \n","color":"#ffffff","alpha":0.6,"rows_above":8}],[{"text":"         ◼◼◼◼◼◼◼◼◼◼◼◼◼◼◼◼◼◼◼◼◼◼◼◼◼◼                      \n        ◼◼◼◼◼  ◼ ◼◼◼◼◼◼◼◼◼◼◼◼◼◼◼◼◼◼◼                     \n        ◼◼◼        ◼◼◼◼◼◼◼◼◼◼◼◼◼◼◼◼◼◼                    \n        ◼◼               ◼◼◼◼◼◼◼◼◼◼◼◼◼                   \n","color":"#ffffff","alpha":0.8,"rows_above":8},{"text":"         ◼◼◼◼◼◼◼◼◼◼◼◼◼◼◼◼◼◼◼◼◼◼◼◼◼◼◼                     \n        ◼◼◼◼       ◼◼◼◼◼◼◼◼◼◼◼◼◼◼◼◼◼◼                    \n        ◼◼        ◼◼◼◼◼◼◼◼◼◼◼◼◼◼◼◼◼◼◼◼                   \n        ◼◼◼             ◼◼◼◼◼◼◼◼◼◼◼◼◼◼◼                  \n","color":"#ffffff","alpha":0.8,"rows_above":8}],[{"text":"◼◼◼◼◼◼◼                                 ◼◼◼◼◼◼◼◼◼◼◼◼◼◼◼◼◼\n◼◼◼◼◼◼◼◼  ◼◼◼         ◼◼                 ◼◼◼◼◼◼◼◼◼◼      \n◼◼ ◼◼◼◼◼     ◼◼◼    ◼◼                    ◼  ◼◼◼◼◼◼◼◼◼◼◼◼\n◼◼ ◼◼◼◼◼◼   ◼ ◼◼                                ◼◼◼◼◼◼◼◼◼\n","color":"#ffffff","alpha":0.2,"rows_above":16},{"text":"◼◼◼◼◼◼◼◼   ◼                            ◼◼◼◼◼◼◼◼◼◼◼◼◼◼◼◼◼\n◼◼◼◼◼◼◼◼    ◼   ◼   ◼◼◼◼                 ◼ ◼           ◼◼\n◼◼ ◼◼◼◼◼     ◼◼◼     ◼◼                        ◼◼◼◼◼◼◼◼◼◼\n◼◼◼◼◼◼◼◼     ◼◼◼                                 ◼◼◼◼ ◼◼◼\n","color":"#ffffff","alpha":0.2,"rows_above":16}],[{"text":"       ◼                               ◼                 \n         ◼   ◼◼◼◼◼◼ ◼◼                  ◼                \n  ◼        ◼◼   ◼  ◼  ◼◼                 ◼ ◼◼            \n  ◼      ◼ ◼       ◼◼ ◼                    ◼             \n","color":"#ffffff","alpha":0.4,"rows_above":16},{"text":"         ◼◼ ◼  ◼◼◼  ◼◼                 ◼                 \n         ◼◼◼ ◼◼◼ ◼ ◼                    ◼                \n  ◼     ◼  ◼◼     ◼◼◼  ◼                   ◼◼◼◼          \n        ◼◼  ◼         ◼                                  \n","color":"#ffffff","alpha":0.4,"rows_above":16}],[{"text":"        ◼ ◼◼◼◼◼◼◼◼◼◼◼◼◼◼◼             ◼                  \n        ◼          ◼    ◼◼◼            ◼                 \n        ◼ ◼      ◼◼      ◼             ◼◼                \n          ◼          ◼ ◼◼◼                ◼ ◼◼◼◼         \n","color":"#ffffff","alpha":0.6,"rows_above":16},{"text":"        ◼    ◼◼   ◼◼  ◼◼◼◼                               \n        ◼         ◼     ◼◼             ◼                 \n         ◼◼             ◼◼              ◼◼◼              \n          ◼◼        ◼◼ ◼◼                  ◼◼            \n","color":"#ffffff","alpha":0.6,"rows_above":16}],[{"text":"         ◼               ◼◼◼◼◼◼◼◼◼◼◼◼◼                   \n                           ◼◼◼◼◼◼◼◼◼◼◼◼                  \n         ◼              ◼ ◼◼◼◼◼◼◼◼◼◼◼◼◼                  \n                ◼◼◼       ◼◼◼◼◼◼◼◼◼◼◼◼◼◼◼◼               \n","color":"#ffffff","alpha":0.8,"rows_above":16},{"text":"                          ◼◼◼◼◼◼◼◼◼◼◼◼◼                  \n                          ◼◼◼◼◼◼◼◼◼◼◼◼◼                  \n                ◼◼        ◼◼◼◼◼◼◼◼◼◼◼◼◼◼                 \n                ◼◼◼◼     ◼◼◼◼◼◼◼◼◼◼◼◼◼◼◼◼◼◼  ◼◼◼◼        \n","color":"#ffffff","alpha":0.8,"rows_above":16}],[{"text":"◼◼ ◼◼◼◼◼     ◼◼                                      ◼◼◼◼\n◼◼ ◼◼◼◼ ◼                                          ◼     \n◼◼ ◼◼◼◼◼◼      ◼◼                                   ◼◼◼◼◼\n◼◼ ◼◼◼◼◼ ◼                                           ◼   \n","color":"#ffffff","alpha":0.2,"rows_above":24},{"text":"◼◼ ◼◼◼◼◼                                            ◼◼◼◼◼\n◼◼ ◼◼◼◼ ◼                                          ◼◼◼◼◼◼\n◼◼ ◼◼◼◼◼◼◼                                           ◼◼◼◼\n◼◼ ◼◼◼◼◼ ◼                                           ◼◼◼◼\n","color":"#ffffff","alpha":0.2,"rows_above":24}],[{"text":"  ◼     ◼◼  ◼  ◼                                    ◼    \n  ◼       ◼   ◼       ◼◼                                 \n  ◼      ◼    ◼  ◼◼◼                               ◼     \n  ◼                                                      \n","color":"#ffffff","alpha":0.4,"rows_above":24},{"text":"  ◼     ◼◼◼  ◼◼       ◼                                  \n  ◼      ◼    ◼◼ ◼  ◼                                    \n  ◼               ◼                                 ◼    \n  ◼                                       ◼              \n","color":"#ffffff","alpha":0.4,"rows_above":24}],[{"text":"          ◼          ◼◼◼                         ◼◼◼     \n         ◼ ◼◼◼ ◼◼◼  ◼   ◼                         ◼      \n          ◼◼◼◼      ◼       ◼                            \n          ◼ ◼    ◼◼◼  ◼                  ◼          ◼    \n","color":"#ffffff","alpha":0.6,"rows_above":24},{"text":"            ◼  ◼     ◼ ◼◼                          ◼     \n          ◼◼◼◼  ◼  ◼ ◼  ◼◼   ◼                    ◼      \n          ◼◼◼◼◼◼◼◼ ◼◼◼                                   \n          ◼      ◼◼◼◼◼◼◼◼                ◼ ◼             \n","color":"#ffffff","alpha":0.6,"rows_above":24}],[{"text":"           ◼    ◼◼◼◼◼   ◼◼◼◼◼◼◼◼◼◼◼◼◼◼◼◼◼◼◼◼◼◼◼◼◼        \n                  ◼◼ ◼   ◼◼◼◼◼◼◼◼◼◼◼◼◼◼◼◼◼◼◼◼◼◼◼◼◼       \n                     ◼◼◼◼◼◼◼ ◼◼◼◼◼◼◼◼◼◼◼◼◼◼◼◼◼◼◼◼◼◼      \n           ◼ ◼◼◼◼   ◼◼ ◼◼◼◼◼◼◼◼◼◼◼◼◼◼◼◼◼◼ ◼◼◼◼◼◼◼◼◼◼     \n","color":"#ffffff","alpha":0.8,"rows_above":24},{"text":"           ◼    ◼◼◼◼◼    ◼◼◼◼◼◼◼◼◼◼◼◼◼◼◼◼◼◼◼◼◼◼◼◼◼◼      \n                  ◼   ◼◼  ◼◼◼ ◼◼◼◼◼◼◼◼◼◼◼◼◼◼◼◼◼◼◼◼       \n                      ◼◼◼◼◼◼◼◼◼◼◼◼◼◼◼◼◼◼◼◼◼◼◼◼◼◼◼◼◼◼     \n           ◼◼◼◼◼◼        ◼◼◼◼◼◼◼◼◼◼◼◼◼◼◼◼   ◼◼◼◼◼◼◼◼◼    \n","color":"#ffffff","alpha":0.8,"rows_above":24}],[{"text":" ◼ ◼ ◼◼  ◼          ◼◼                    ◼◼          ◼◼◼\n◼◼ ◼◼◼◼◼◼◼         ◼◼                                    \n◼◼ ◼◼◼◼◼◼◼                                  ◼            \n◼◼◼◼◼◼◼◼◼                                 ◼              \n","color":"#ffffff","alpha":0.2,"rows_above":32},{"text":"◼◼ ◼ ◼   ◼         ◼◼◼◼                    ◼◼        ◼◼◼◼\n◼◼ ◼◼◼◼◼ ◼        ◼◼                        ◼          ◼◼\n◼◼◼◼◼◼◼◼◼                                                \n◼◼◼◼◼◼◼◼◼                                ◼  ◼            \n","color":"#ffffff","alpha":0.2,"rows_above":32}],[{"text":"  ◼       ◼        ◼  ◼◼                             ◼   \n  ◼       ◼      ◼◼  ◼◼◼◼◼                 ◼◼◼           \n  ◼              ◼◼◼                       ◼ ◼          ◼\n         ◼                               ◼ ◼◼◼           \n","color":"#ffffff","alpha":0.4,"rows_above":32},{"text":"  ◼       ◼       ◼    ◼                                 \n  ◼              ◼  ◼◼  ◼◼                ◼◼ ◼        ◼  \n         ◼        ◼                       ◼◼◼◼           \n         ◼                                ◼◼             \n","color":"#ffffff","alpha":0.4,"rows_above":32}],[{"text":"           ◼     ◼◼     ◼                ◼  ◼◼           \n                          ◼               ◼   ◼    ◼◼    \n                ◼   ◼◼◼◼◼◼                ◼   ◼◼◼◼     ◼ \n          ◼    ◼◼◼◼◼◼ ◼                 ◼     ◼◼◼◼◼◼◼◼◼  \n","color":"#ffffff","alpha":0.6,"rows_above":32},{"text":"                ◼◼      ◼◼                ◼  ◼  ◼◼◼◼◼    \n          ◼     ◼     ◼◼  ◼                   ◼◼◼    ◼   \n                ◼◼ ◼◼◼◼◼◼                ◼    ◼◼◼◼◼◼     \n          ◼    ◼◼◼◼◼◼                  ◼◼    ◼◼◼◼◼◼◼◼◼◼◼◼\n","color":"#ffffff","alpha":0.6,"rows_above":32}],[{"text":"            ◼◼◼◼◼        ◼◼◼◼◼◼◼◼◼◼◼◼◼◼◼◼     ◼◼◼◼◼◼◼    \n           ◼◼◼◼◼◼          ◼◼◼◼◼◼◼◼◼◼◼◼◼◼◼     ◼◼◼◼      \n          ◼◼◼◼◼◼          ◼◼◼◼◼◼◼◼◼◼◼◼◼◼◼◼        ◼◼◼◼◼  \n           ◼◼◼◼      ◼ ◼◼◼◼◼◼◼◼◼◼◼◼◼◼◼◼◼               ◼◼\n","color":"#ffffff","alpha":0.8,"rows_above":32},{"text":"           ◼◼◼◼◼          ◼◼◼◼◼◼◼◼◼◼◼◼◼◼◼◼    ◼◼         \n           ◼◼◼◼◼           ◼◼◼◼◼◼◼◼◼◼◼◼◼◼◼       ◼◼◼◼    \n          ◼◼◼◼◼◼         ◼◼◼◼◼◼◼◼◼◼◼◼◼◼◼◼           ◼◼◼◼◼\n           ◼◼◼◼      ◼◼◼◼◼◼◼◼◼◼◼◼◼◼◼◼◼◼                  \n","color":"#ffffff","alpha":0.8,"rows_above":32}],[{"text":"◼◼◼◼◼◼◼◼                                  ◼              \n◼◼◼◼◼                                   ◼◼               \n◼◼◼                                        ◼             \n◼◼        ◼                               ◼              \n","color":"#ffffff","alpha":0.2,"rows_above":40},{"text":"◼◼◼◼◼◼ ◼                                 ◼◼              \n◼◼◼◼◼                                    ◼◼              \n◼◼◼        ◼                              ◼◼             \n◼◼      ◼◼◼                               ◼              \n","color":"#ffffff","alpha":0.2,"rows_above":40}],[{"text":"         ◼                               ◼ ◼◼            \n      ◼                                ◼  ◼ ◼    ◼       \n   ◼       ◼                           ◼◼◼◼ ◼◼◼◼◼◼◼   ◼  \n  ◼◼    ◼◼ ◼                             ◼ ◼ ◼◼◼◼◼  ◼◼   \n","color":"#ffffff","alpha":0.4,"rows_above":40},{"text":"        ◼                               ◼  ◼◼            \n                                       ◼◼  ◼◼   ◼◼◼      \n   ◼      ◼                            ◼◼◼  ◼◼◼◼◼◼   ◼   \n  ◼◼   ◼   ◼◼                          ◼◼◼ ◼◼◼◼◼◼◼  ◼ ◼  \n","color":"#ffffff","alpha":0.4,"rows_above":40}],[{"text":"                                       ◼◼    ◼◼◼◼◼◼◼◼◼◼◼◼\n        ◼◼                                 ◼ ◼◼◼◼ ◼◼◼◼◼◼◼\n    ◼  ◼  ◼ ◼                        ◼◼            ◼◼◼ ◼◼\n       ◼    ◼                       ◼◼◼◼◼   ◼     ◼◼  ◼◼◼\n","color":"#ffffff","alpha":0.6,"rows_above":40},{"text":"         ◼◼       ◼                    ◼     ◼◼◼◼◼◼◼◼◼◼ ◼\n     ◼ ◼◼ ◼◼◼◼                               ◼◼◼   ◼◼◼◼◼◼\n    ◼ ◼  ◼  ◼                       ◼◼◼           ◼◼◼ ◼◼◼\n      ◼                             ◼◼◼           ◼◼ ◼ ◼◼\n","color":"#ffffff","alpha":0.6,"rows_above":40}],[{"text":"          ◼◼◼◼◼◼◼◼◼◼◼◼◼◼◼◼◼◼◼◼◼◼◼◼◼◼◼◼◼                  \n       ◼  ◼◼◼◼◼◼◼◼◼◼◼◼◼◼◼◼◼◼◼◼◼◼◼◼◼◼◼◼◼                  \n     ◼◼ ◼◼   ◼◼◼◼◼◼◼◼◼◼◼◼◼◼◼◼◼◼◼◼◼◼◼◼                    \n    ◼◼◼      ◼◼◼◼◼◼◼◼◼◼◼◼◼◼◼◼◼◼◼◼◼◼◼                     \n","color":"#ffffff","alpha":0.8,"rows_above":40},{"text":"           ◼◼◼◼◼◼◼ ◼◼◼◼◼◼◼◼◼◼◼◼◼◼◼◼◼◼◼◼                ◼ \n      ◼  ◼    ◼◼◼◼◼◼◼◼◼◼◼◼◼◼◼◼◼◼◼◼◼◼◼◼◼                  \n     ◼ ◼◼    ◼◼◼◼◼◼◼◼◼◼◼◼◼◼◼◼◼◼◼◼◼◼◼                     \n    ◼◼       ◼◼◼◼◼◼◼◼◼◼◼◼◼◼◼◼◼◼◼◼◼◼◼                     \n","color":"#ffffff","alpha":0.8,"rows_above":40}],[{"text":"◼       ◼◼◼                              ◼    ◼          \n◼       ◼◼◼                             ◼◼  ◼◼           \n◼    ◼ ◼◼◼                               ◼ ◼◼      ◼     \n    ◼◼ ◼◼◼  ◼◼                          ◼  ◼◼ ◼   ◼◼◼    \n","color":"#ffffff","alpha":0.2,"rows_above":48},{"text":"◼       ◼◼◼                             ◼◼   ◼           \n◼      ◼◼◼                               ◼  ◼       ◼    \n    ◼◼ ◼◼◼                              ◼  ◼◼     ◼◼ ◼   \n    ◼◼◼◼◼◼  ◼                          ◼◼     ◼   ◼      \n","color":"#ffffff","alpha":0.2,"rows_above":48}],[{"text":" ◼◼◼   ◼   ◼                           ◼◼ ◼ ◼◼ ◼◼◼ ◼◼◼◼◼◼\n  ◼ ◼◼ ◼   ◼◼                          ◼  ◼◼  ◼◼◼◼◼◼◼◼◼  \n ◼◼◼◼ ◼   ◼◼◼◼                        ◼◼◼    ◼◼◼◼◼◼ ◼◼◼◼ \n◼ ◼◼  ◼   ◼◼                           ◼ ◼◼  ◼ ◼◼    ◼   \n","color":"#ffffff","alpha":0.4,"rows_above":48},{"text":" ◼◼◼   ◼   ◼                              ◼ ◼ ◼◼◼◼ ◼◼◼◼◼◼\n  ◼ ◼◼    ◼◼◼                         ◼◼◼  ◼ ◼◼◼◼◼◼◼ ◼ ◼◼\n◼ ◼◼  ◼   ◼◼◼◼                        ◼◼ ◼◼  ◼◼◼◼◼  ◼ ◼◼ \n  ◼◼      ◼◼ ◼  ◼           ◼         ◼  ◼◼ ◼◼ ◼   ◼◼    \n","color":"#ffffff","alpha":0.4,"rows_above":48}],[{"text":"     ◼◼     ◼                        ◼◼    ◼      ◼      \n ◼ ◼  ◼      ◼◼                       ◼                ◼◼\n              ◼                      ◼    ◼             ◼\n ◼            ◼◼◼      ◼ ◼◼◼◼◼◼◼◼◼  ◼◼◼               ◼◼◼\n","color":"#ffffff","alpha":0.6,"rows_above":48},{"text":"    ◼◼◼     ◼                        ◼◼◼   ◼      ◼      \n ◼ ◼  ◼      ◼◼                      ◼    ◼           ◼  \n ◼             ◼◼      ◼            ◼◼                  ◼\n◼◼            ◼◼ ◼      ◼◼◼◼ ◼◼◼◼◼ ◼◼◼               ◼◼◼◼\n","color":"#ffffff","alpha":0.6,"rows_above":48}],[{"text":"    ◼        ◼◼◼◼◼◼◼◼◼◼◼◼◼◼◼◼◼◼◼◼◼◼◼◼                    \n               ◼◼◼◼◼◼◼◼◼◼◼◼◼◼◼◼◼◼◼◼◼◼◼                   \n               ◼◼◼◼◼◼◼◼◼◼◼◼◼◼◼◼◼◼◼◼◼◼                    \n                 ◼◼◼◼◼◼ ◼         ◼◼                     \n","color":"#ffffff","alpha":0.8,"rows_above":48},{"text":"             ◼◼◼◼◼◼◼◼◼◼◼◼◼◼◼◼◼◼◼◼◼◼◼◼                    \n               ◼◼◼◼◼◼◼◼◼◼◼◼◼◼◼◼◼◼◼◼◼◼                    \n              ◼  ◼◼◼◼◼◼ ◼◼◼◼◼◼◼◼◼◼◼◼                     \n                  ◼◼◼◼◼◼          ◼                      \n","color":"#ffffff","alpha":0.8,"rows_above":48}],[{"text":"    ◼◼◼◼◼   ◼    ◼                     ◼◼ ◼   ◼◼ ◼       \n   ◼◼◼◼◼   ◼◼                         ◼◼◼ ◼◼◼◼           \n","color":"#ffffff","alpha":0.2,"rows_above":56},{"text":"    ◼◼◼◼   ◼◼   ◼                   ◼◼ ◼◼ ◼  ◼◼ ◼        \n   ◼◼◼◼◼  ◼◼◼  ◼◼ ◼           ◼  ◼◼  ◼◼◼◼ ◼◼◼  ◼         \n","color":"#ffffff","alpha":0.2,"rows_above":56}],[{"text":"  ◼◼     ◼◼◼ ◼ ◼◼            ◼◼    ◼◼◼◼  ◼  ◼◼    ◼◼◼◼◼  \n ◼◼     ◼◼◼   ◼◼◼◼◼◼       ◼◼◼◼  ◼◼◼◼◼   ◼      ◼◼◼◼◼◼◼  \n","color":"#ffffff","alpha":0.4,"rows_above":56},{"text":" ◼◼◼    ◼◼◼  ◼ ◼ ◼         ◼◼◼◼       ◼  ◼  ◼    ◼◼◼◼◼  ◼\n ◼◼     ◼◼    ◼  ◼       ◼◼◼◼◼     ◼◼    ◼      ◼◼◼ ◼    \n","color":"#ffffff","alpha":0.4,"rows_above":56}],[{"text":"◼◼            ◼   ◼  ◼ ◼◼◼◼◼◼  ◼◼◼◼                    ◼◼\n◼            ◼        ◼◼◼◼◼    ◼◼                      ◼◼\n","color":"#ffffff","alpha":0.6,"rows_above":56},{"text":"◼             ◼   ◼◼   ◼◼◼◼    ◼◼◼◼◼                  ◼◼ \n◼            ◼     ◼ ◼◼◼◼      ◼◼                  ◼ ◼◼◼◼\n","color":"#ffffff","alpha":0.6,"rows_above":56}],[{"text":"                   ◼◼ ◼                                  \n                    ◼◼                                   \n","color":"#ffffff","alpha":0.8,"rows_above":56},{"text":"                    ◼◼◼                                  \n                    ◼                                    \n","color":"#ffffff","alpha":0.8,"rows_above":56}]]